{
    "installer":  {
                      "url":  "https://raw.githubusercontent.com/getiton85/gerinogi-routine-runner/main/installers/%EB%A7%88%EC%8A%A4%ED%81%AC%ED%85%8C%EC%8A%A4%ED%8A%B8%20%EC%84%A4%EC%B9%98_1.0.48.exe",
                      "sha256":  "63938056a1dec9d38e8ad3fbf0c5db791dd8ba412bd7cd9cc84dfebde1135636",
                      "file":  "마스크테스트 설치_1.0.48.exe"
                  },
    "version":  "1.0.53",
    "update_mode":  "package",
    "package":  {
                    "url":  "https://raw.githubusercontent.com/getiton85/gerinogi-routine-runner/main/mask-auto/packages/gerinogi_mask_update_package_1.0.53_complete_visual_gate_fix.zip",
                    "sha256":  "e2e612a7e8c78d93e87c5ec998642d4f181a9c6ad0151eb8fc8653ba5fd1a627",
                    "files":  [
                                  "local_state_routine_runner.ps1"
                              ]
                },
    "notes":  [
                  "자동1 완료 확인 단계에서 gate가 이미지 검색 자체를 막던 구조 수정",
                  "완료 확인 이미지를 안정적으로 2회 확인하면 보수 gate보다 시각 확인을 우선",
                  "완료 확인 밝은 글자 기준만 86%에서 82%로 조정하고 기존 경로/전투 루틴은 유지"
              ]
}
