{
    "version":  "1.0.103",
    "update_mode":  "package",
    "required_reinstall":  false,
    "package":  {
                    "url":  "https://raw.githubusercontent.com/getiton85/gerinogi-routine-runner/main/packages/gerinogi_update_package_1.0.103_any_dungeon_start_guard.zip",
                    "sha256":  "db2d2fc6ac9e49e31e680ee838228e3f2612df01246e48d06b0dca951550795e",
                    "size":  1422349,
                    "files":  [
                                  "local_state_routine_runner.ps1",
                                  "state_samples"
                              ]
                },
    "notes":  [
                  "Allow start when any dungeon routine is ON",
                  "Use all selected dungeon routines instead of Harbor-only start guard",
                  "Keep existing combat, coop, skip, and click routines unchanged"
              ]
}